{"_path":"/ai-fiction/登棋仙途/10-月下密谈","title":"第10章 月下密谈","date":"","novelSlug":"登棋仙途","novelName":"登棋仙途","chapterFile":"10-月下密谈","body":"<h1>第10章 月下密谈</h1>\n<p>主峰静室的门被推开时，沈砚正在调息。</p>\n<p>传音符落在掌心，玄微真人的声音温和如常：&quot;砚儿，来静室一趟。&quot;</p>\n<p>没有解释原因，没有说明急缓。但沈砚看见传音符上缠绕的气运线在轻微颤动，那是玄微真人情绪波动的痕迹。</p>\n<p>他起身，整理衣袍，将掌心态印藏入袖中。</p>\n<p>夜色已深，主峰上只有几盏长明灯亮着。沈砚穿过回廊，脚步放得很轻。沿途的弟子都已歇息，只有他的影子被月光拉得很长，投射在青石板上。</p>\n<p>静室位于主峰后山，是一处独立的院落。沈砚站在门外，深吸一口气，抬手叩门。</p>\n<p>&quot;进来。&quot;</p>\n<p>玄微真人的声音从室内传来。</p>\n<p>沈砚推门而入。</p>\n<p>静室内点着一炉香，烟气袅袅上升，在月光下形成淡青色的雾霭。玄微真人坐在窗边的蒲团上，面前摆着一张小几，几上有两杯茶。</p>\n<p>&quot;师尊。&quot;沈砚行礼。</p>\n<p>&quot;坐。&quot;玄微真人指了指对面的蒲团，&quot;今夜月色不错，陪为师喝杯茶。&quot;</p>\n<p>沈砚依言坐下，目光扫过那两杯茶。茶水尚温，显然是刚泡好的。玄微真人早就预料他会来。</p>\n<p>&quot;小比的事，为师听说了。&quot;玄微真人端起茶杯，轻轻吹了吹，&quot;三轮全胜，进入前十三。不错。&quot;</p>\n<p>&quot;侥幸而已。&quot;沈砚道。</p>\n<p>&quot;侥幸？&quot;玄微真人看了他一眼，眼神温和中带着审视，&quot;连胜三轮，每轮都用不同的战术。第一轮速战速决，第二轮消耗对手，第三轮……你故意卖了个破绽，引王崇上钩。&quot;</p>\n<p>沈砚心中一凛。</p>\n<p>那场比试，他确实故意露出破绽。王崇修为比他高两层，正面硬拼没有胜算。他只能诱敌深入，在关键时刻反制。</p>\n<p>但这个细节，玄微真人是如何知道的？</p>\n<p>&quot;弟子只是随机应变。&quot;沈砚垂下眼帘。</p>\n<p>&quot;随机应变？&quot;玄微真人轻笑，&quot;那为师问你，你现在的修为，到了什么境界？&quot;</p>\n<p>沈砚握杯的手指微微收紧。</p>\n<p>这是试探。</p>\n<p>他压下掌心态印的悸动，控制着气运的流动，不让任何异常泄露出去。</p>\n<p>&quot;练气六层。&quot;他如实回答。</p>\n<p>&quot;六层……&quot;玄微真人抿了口茶，目光落在沈砚脸上，&quot;但你突破的时机，有些奇怪。为师记得，你修炼气运之法不过十余日，就从练气四层到了六层。这个速度，即便是气运子，也过于快了。&quot;</p>\n<p>&quot;或许是弟子资质尚可。&quot;沈砚道。</p>\n<p>&quot;资质？&quot;玄微真人放下茶杯，指尖在几面上轻轻敲击，&quot;砚儿，你可知&#39;气运子&#39;三个字，意味着什么？&quot;</p>\n<p>沈砚抬起头，迎上玄微真人的目光。</p>\n<p>那双眼睛里没有杀意，没有恶意，只有一种复杂的、难以名状的情绪。像是在看一个即将远行的孩子，又像是在评估一件即将成熟的器物。</p>\n<p>&quot;意味着弟子的运气比常人好一些。&quot;沈砚说。</p>\n<p>&quot;只是运气？&quot;</p>\n<p>&quot;还有……责任。&quot;沈砚斟酌着词句，&quot;弟子既被选为气运子，就应当努力修行，不辜负宗门的期望。&quot;</p>\n<p>玄微真人沉默了片刻。</p>\n<p>窗外的月光洒进来，照在他半张脸上。那张平日里温和的脸，此刻在光影中显得有些模糊，像是隔了一层薄纱。</p>\n<p>&quot;责任。&quot;玄微真人重复了一遍，忽然笑了，&quot;你说得对。气运子确实有责任。但你可知道，这份责任的终点在哪里？&quot;</p>\n<p>沈砚的心跳漏了一拍。</p>\n<p>这是最危险的试探。如果回答错了，可能会暴露他已经知道收割的真相。</p>\n<p>他低下头，看着杯中的茶水。茶水倒映着月光，也倒映着他的脸。那张脸上没有任何异常，只有年轻人特有的、对未来的迷茫与期待。</p>\n<p>&quot;弟子不知。&quot;沈砚说，&quot;但弟子相信，师尊不会害我。&quot;</p>\n<p>玄微真人的手指停住了。</p>\n<p>这句话像是一颗石子，投入了平静的湖面。沈砚看见玄微真人眼底闪过一丝波动，那是真实的情感，不是伪装。</p>\n<p>&quot;为师……&quot;玄微真人顿了顿，声音低了几分，&quot;为师确实不会害你。&quot;</p>\n<p>他伸手，从袖中取出一个小玉瓶，推到沈砚面前。</p>\n<p>&quot;这是&#39;凝神丹&#39;，能帮助你稳固境界。你近日修为增长太快，根基不稳。服下此丹，可避免走火入魔。&quot;</p>\n<p>沈砚接过玉瓶，指尖触碰到瓶身时，他感知到玉瓶上缠绕着一丝极细的气运线。那气运线连接着玄微真人，也连接着某个更遥远的存在。</p>\n<p>像是某种标记。</p>\n<p>&quot;多谢师尊。&quot;沈砚收好玉瓶。</p>\n<p>&quot;砚儿。&quot;玄微真人忽然唤他，&quot;为师问你一个问题。&quot;</p>\n<p>&quot;师尊请讲。&quot;</p>\n<p>&quot;若有一日，你发现修行的真相与你想象的不同……&quot;玄微真人顿了顿，目光深邃，&quot;你会如何选择？&quot;</p>\n<p>沈砚的手指在袖中微微蜷缩。</p>\n<p>这个问题，比之前所有的试探都要危险。玄微真人不是在问修行，是在问立场。</p>\n<p>他抬起头，露出一个年轻人该有的、略带困惑的表情。</p>\n<p>&quot;弟子不明白师尊的意思。&quot;沈砚说，&quot;修行的真相，不就是追求长生，追求大道吗？&quot;</p>\n<p>玄微真人看着他，许久没有说话。</p>\n<p>静室里只有香炉里的烟气在缓缓上升，月光在地板上移动了一寸。</p>\n<p>&quot;是啊。&quot;玄微真人最终说道，声音里带着一丝疲惫，&quot;追求长生，追求大道。你说得对。&quot;</p>\n<p>他站起身，走到窗边，背对着沈砚。</p>\n<p>&quot;夜深了，你回去歇息吧。明日还有事。&quot;</p>\n<p>&quot;是。&quot;沈砚起身行礼，退出静室。</p>\n<hr>\n<p>回到住所时，已是子时。</p>\n<p>沈砚关上门，没有点灯，直接盘膝坐在床上。他保持着调息的姿势，呼吸平稳，心跳放缓，像是已经入睡。</p>\n<p>但他没有睡。</p>\n<p>掌心态印贴在床板上，感知着周围气运的流动。他在等。</p>\n<p>等了约莫半个时辰，门外传来极轻的脚步声。</p>\n<p>玄微真人来了。</p>\n<p>沈砚继续维持着熟睡的状态，控制着呼吸的频率，不让任何破绽泄露。</p>\n<p>门被轻轻推开，玄微真人的身影出现在门口。他没有进来，只是站在门外，隔着夜色看向沈砚。</p>\n<p>月光下，玄微真人的表情很复杂。</p>\n<p>他抬起手，指尖凝聚出一道微弱的神念。那道神念没有惊动沈砚，而是化作传音，在静夜里回荡。</p>\n<p>&quot;弈天师兄。&quot;</p>\n<p>玄微真人在对某人传音。</p>\n<p>沈砚的心跳在那一刻几乎停止。他用尽全力控制着身体，不让任何肌肉颤动。</p>\n<p>&quot;这一代的果实，似乎有些不一样。&quot;玄微真人的声音很轻，带着犹豫，&quot;他对气运的感知，远超常人。今日我试探他，他回答得滴水不漏，但……太完美了。&quot;</p>\n<p>门外陷入短暂的沉默。</p>\n<p>沈砚感知到，玄微真人在等待回应。</p>\n<p>&quot;我知道。&quot;玄微真人继续说，&quot;但此子是我徒弟。七年……我教了他七年。&quot;</p>\n<p>七年？</p>\n<p>沈砚心中一震。</p>\n<p>他来青云宗不过数月，玄微真人为何说七年？</p>\n<p>&quot;我明白。&quot;玄微真人的声音更低了，&quot;若真有异常，我会亲自处理。只是……再给我一些时间。&quot;</p>\n<p>他顿了顿，看向屋内的沈砚。</p>\n<p>月光透过窗棂，照在沈砚脸上。那张脸年轻、平静，没有任何异常。</p>\n<p>&quot;希望是我多心了。&quot;玄微真人轻声说，&quot;希望这一代的果实，能顺利成熟。&quot;</p>\n<p>他转身，身影消失在夜色中。</p>\n<p>沈砚又等了半个时辰，确认玄微真人真的离开后，才缓缓睁开眼睛。</p>\n<p>黑暗中，他的瞳孔微微收缩。</p>\n<p>七年。</p>\n<p>玄微真人说教了他七年。</p>\n<p>可他来青云宗，明明只有几个月。</p>\n<p>除非……玄微真人说的&quot;七年&quot;，不是从他入门算起，而是从更早的时候。从他还在边陲小镇，甚至从他出生之前就开始计算。</p>\n<p>沈砚坐起身，掌心印记在黑暗中发出微弱的光。</p>\n<p>那光芒很淡，像是一簇即将熄灭的火。</p>\n<p>他低头看着掌印，忽然想起命石最初认主时，脑海中浮现的那个画面。</p>\n<p>那个站在棋盘前的男子，那个警告他&quot;别再信他们&quot;的声音。</p>\n<p>&quot;你不是第一个，也不会是最后一个。&quot;</p>\n<p>沈砚握紧拳头，掌印的光芒在指缝间闪烁。</p>\n<p>窗外，夜风吹过竹林，发出沙沙的声响。</p>\n<p>远处主峰的方向，一道黑色气运线在夜空中若隐若现，像是某种倒计时。</p>\n<p>沈砚忽然笑了。</p>\n<p>笑声很轻，在寂静的房间里回荡。</p>\n<p>&quot;七年。&quot;他低声说，&quot;那就看看，这七年到底是谁在布局。&quot;</p>\n<p>掌印在这一刻剧烈发烫，像是在回应他的话语。</p>\n<p>黑暗中，沈砚的眼里闪过一丝决绝。</p>\n<p>他需要更快变强。</p>\n<p>需要弄清楚玄微真人说的&quot;七年&quot;是什么意思。</p>\n<p>需要找到破局的方法。</p>\n<p>时间不多了。</p>\n<p>那道黑色气运线在夜空中微微颤动，像是在催促，像是在警告。</p>\n<p>沈砚闭上眼，开始调息。</p>\n<p>明日，他还有事要做。</p>\n"}