{"_path":"/ai-fiction/登棋仙途/01-雨夜收尸","title":"第一章 雨夜收尸","date":"","novelSlug":"登棋仙途","novelName":"登棋仙途","chapterFile":"01-雨夜收尸","body":"<p>第一章 雨夜收尸</p>\n<p>麻绳猛地一绷，沈砚肩背往后一沉，脚下烂泥被拖出两道深沟。断墙下那具尸体卡在碎梁和砖块间，半边身子泡得发胀，他再使一把力，尸身才猛地滑出来，脊骨擦过石棱，发出一串让人牙酸的轻响。</p>\n<p>“轻点！”后头有人骂，“拖烂了还怎么认人？”</p>\n<p>沈砚没回头，只把绳子往腕上又缠了一圈。麻绳早叫雨水和尸油泡得发滑，勒进肉里，火辣辣地疼。他蹲下去，膝盖顶住尸体肩窝，把人翻过来。</p>\n<p>不是村里人。</p>\n<p>村民的手多半粗，指节宽，掌心有茧。这人手指修长，指甲修得很齐，虎口和食指根却磨出一层薄硬茧，像是常年握剑。身上外袍早被扒走，只剩一层灰白里衣，胸口裂开一道口子，血泡进雨里，成了黑红色。腰侧还有一道焦痕，边缘卷曲，不像火烧，倒像被什么东西硬生生烫穿的。</p>\n<p>沈砚手指停了一瞬。</p>\n<p>“阿砚，磨蹭什么呢？”</p>\n<p>收尸的老邢撑着油纸伞站在外头，伞边不断往下滴水。他瘸着一条腿，脸上一道旧刀疤被雨泡得发白，眼睛却亮，像总在死人身上找活路的野狗。“能认的先放东边祠堂，认不出的剥干净了埋后山。今夜埋不完，明早官差来，你们一文钱都拿不着。”</p>\n<p>“知道了。”沈砚应了一声。</p>\n<p>声音不高，落在雨里，像块石子沉进泥水。</p>\n<p>这个村子昨夜才烧透，今夜就只剩一地湿黑的炭和焦肉味。屋梁塌了，墙被劈开，鸡犬死绝，血混着雨，从巷口一路淌到村正家门前。能被亲眷认出来的尸首，白天已经哭着拖走了。剩下这些不是脸烂了，就是胳膊腿不全，再不济，连衣裳都给摸得干净，只能论斤似的拖去乱葬坑。</p>\n<p>死人也分贵贱。</p>\n<p>有家人来认的，叫收殓。</p>\n<p>没家人认的，叫清坑。</p>\n<p>清坑的人，连哭都嫌费嗓子。</p>\n<p>沈砚伸手去摸那修士胸前的伤口，指腹才碰到衣料，一股凉意顺着手指往上窜，像蛇钻进骨头。他眼皮一抬，先看四周。</p>\n<p>院里还有两个一起干活的闲汉，一个在翻灶台，一个在掰死人牙齿，想看有没有金。老邢正隔着雨骂人，没谁注意他。</p>\n<p>沈砚这才慢慢把那层里衣撕开。</p>\n<p>尸体胸口皮肉翻卷，肋骨断了两根，心口位置却嵌着一点黑。</p>\n<p>半枚指甲盖大的碎片，乌沉沉的，表面像烧过的瓷，又像金属。雨水打在上头，一点也挂不住，顺着边缘滚开。碎片旁边的血肉没有腐烂，反倒收得很紧，像被什么东西吊着，不肯散。</p>\n<p>沈砚喉结轻轻动了一下。</p>\n<p>这不是村里人能有的东西。</p>\n<p>更不是老邢该看见的东西。</p>\n<p>他两指探进去，捏住那半枚黑片。皮肉已经半僵，碎片却温得邪门，像人刚捂热的铜钱。拔出来时，尸体喉咙里“咯”了一声，雨声像是一下子远了。</p>\n<p>沈砚动作没停，顺势将黑片压进袖中，另一只手在尸体颈侧一抹，把扯出来的血水抹匀，遮住空处。做完这些，他才抬头喊：“这边一个外来的，不好认。”</p>\n<p>“外来的扒干净就埋！”老邢在雨里吼，“鞋底要是厚，鞋给我留着！”</p>\n<p>“好。”</p>\n<p>沈砚应完，心跳却没有落下去。</p>\n<p>那半枚黑片贴在腕骨边，烫意一阵一阵往里钻。他不动声色地把袖口拢紧，拖着尸体往外走。经过塌掉的门槛时，地上有一截烧断的木柱，尸体脑袋撞上去，发出闷响。</p>\n<p>后面掰牙那个闲汉抬头看了眼，啧了一声：“你轻点，回头脑浆都给你颠出来。”</p>\n<p>沈砚没搭理。</p>\n<p>死人脑浆流不流，跟活人领不领工钱没关系。可袖子里这东西，不该在这儿。</p>\n<p>他把尸体拖到祠堂外的空地，和另外几具认不出的堆在一起，刚直起身，就听见“啪”一声脆响。</p>\n<p>一个瘦猴似的闲汉从旁边窜出来，手里攥着块玉牌，眼睛发亮：“老邢！我摸着一个这个！”</p>\n<p>老邢瘸着腿赶过去，一把夺下玉牌，拿袖子擦了擦，脸色先是一喜，随即又沉下来：“裂了。裂成这样，不值钱。”</p>\n<p>瘦猴不干了：“不值钱你抢什么？”</p>\n<p>“我抢？”老邢抬手就是一巴掌，抽得人原地打转，“你们吃住谁给的？铁锹谁买的？今夜不是我带你们进来，你连这村门都摸不着！死人财也轮得着你分？”</p>\n<p>瘦猴捂着脸，不敢再叫，只敢低声咒骂。</p>\n<p>另一边掰牙的闲汉嘿嘿笑：“你要不服，自己去官道上捡尸。”</p>\n<p>老邢把那块裂玉往怀里一揣，扫了眼众人：“都给我听清了。今晚收着什么，先过我眼。谁敢偷摸往自己身上藏，埋坑的时候我连人一块埋。”</p>\n<p>他说这话时，目光在沈砚身上停了停。</p>\n<p>停得很短。</p>\n<p>沈砚却看见了。</p>\n<p>老邢一直防他。不是因为他话少，是因为他手稳，眼睛又毒。村里死了谁，谁衣角少了半寸布，谁手指上原先戴过戒，沈砚扫一眼就能记住。老邢这种人，最怕手下有脑子。</p>\n<p>沈砚垂下眼，弯腰继续干活。袖中那半枚黑片贴着皮肤，热意慢慢退了，换成一种潮冷，像从骨缝里生出来。</p>\n<p>他拖到第三具尸体时，听见身后有人低低说了一句。</p>\n<p>“还给我。”</p>\n<p>沈砚手一顿。</p>\n<p>雨还在下，滴在断瓦上、破鼓上、半塌的祠堂匾额上，四处都是响。他侧过头，只看见祠堂门口挂着半截白幡，被雨打得贴在柱子上，像张烂脸。</p>\n<p>没人。</p>\n<p>“听见没有？”瘦猴在不远处骂骂咧咧，“你拿老子的那把铁钩做什么？”</p>\n<p>“谁拿你铁钩了？”</p>\n<p>两人很快吵起来。</p>\n<p>像是刚才那句只是雨错了声。</p>\n<p>沈砚继续拖尸，步子却慢了些。等他把这一具丢进待埋的尸堆里，袖口忽然一沉，像有什么东西从里头坠了一下。</p>\n<p>那不是碎片该有的分量。</p>\n<p>他立刻转身，借着整理麻绳的动作把手探进去。半枚黑片还在，只是边缘多了一圈湿滑触感，像刚从人嘴里捞出来。</p>\n<p>沈砚把手抽出来时，指尖沾了点黑红色的黏液。</p>\n<p>不是他的血。</p>\n<p>“阿砚！”老邢在院外喊，“村正家那边还压着一具，你去。”</p>\n<p>沈砚把手在裤腿上擦净，拎起麻绳过去。</p>\n<p>村正家的宅子烧得最狠。门梁塌了，堂屋的屏风倒进火盆里，烧成一团蜷曲的黑架。地上躺着几具尸首，烧焦的，砸烂的，脸全不成样。村正一家昨夜死得整整齐齐，白天却没人敢来认，怕沾上灭门的晦气，也怕官差问话。于是拖到现在，还在泥里泡着。</p>\n<p>沈砚跨过门槛，脚底踩到什么，咔嚓一声。</p>\n<p>是一只小孩的木陀螺，烧掉半边，红漆还剩一点。</p>\n<p>他把脚挪开，抬眼看向堂屋深处。</p>\n<p>最里面压着个男人，半边身子埋在梁木下，头歪在一边，官帽早没了，只剩发髻散在泥里。这就是村正。</p>\n<p>三天前，沈砚还见过他。</p>\n<p>那时村正穿着一身簇新的夹袍，站在晒谷场上清点粮税，嫌谁家交得少，抬脚就踹。踹的正是沈砚寄住那户寡妇家的门板。老太太跪在地上求，说孙子病着，求缓两日。村正嫌她哭得脏耳朵，转头叫人把家里仅剩的半袋黍米抬走了。</p>\n<p>第二天夜里，村子就让人屠了。</p>\n<p>沈砚走过去，把梁木往上抬了抬。木头吸饱了雨，又沉又滑，底下的尸体被压得肚腹裂开，泛出臭味。他屏住气，把绳子套上村正脚踝，正要往外拖，耳边又响起那道声音。</p>\n<p>“冷……”</p>\n<p>这次近得像贴着后颈。</p>\n<p>沈砚猛地回身，手已经摸到腰后短刀。刀只有半尺，是劈柴磨出来的，刀刃卷着口。堂屋里没有人，门口雨幕斜斜挂下来，像一层灰白帘子。地上几具死人都老实趴着，没谁能开口。</p>\n<p>可那股冷意更重了。</p>\n<p>袖中的半枚黑片像活了一样，轻轻一跳。</p>\n<p>下一瞬，堂屋角落传来“嗒”的一声。</p>\n<p>像有人赤脚踩在湿地上。</p>\n<p>沈砚盯着那片黑，没动。</p>\n<p>第二声紧跟着响起。</p>\n<p>嗒。</p>\n<p>第三声。</p>\n<p>嗒。</p>\n<p>声音越来越近，不快，也不急，像有人在屋里绕着他慢慢走。可地上没有脚印，雨线里也没有影子。沈砚能听见自己的呼吸，听见屋檐水砸在木盆里的空响，听见梁木烧裂后残存的焦味被雨水泡开。</p>\n<p>他忽然明白过来。</p>\n<p>不是有人在走。</p>\n<p>是地上的尸体，在滴水。</p>\n<p>滴在不同地方，连成了脚步声。</p>\n<p>沈砚额角绷紧，手心全是汗。他往后退了半步，脚跟撞上翻倒的供桌。供桌腿一歪，啪地倒下去，露出桌底一个缩着的黑影。</p>\n<p>那是个老妇人，头皮被火燎得卷起，眼皮半睁，嘴却裂得很大，像死前还在喊。她本该早就凉透了，可供桌一倒，她喉咙里忽然滚出一串水泡似的音节。</p>\n<p>“还……给……我……”</p>\n<p>沈砚一把拔出短刀。</p>\n<p>老妇人的眼珠浑浊，直勾勾对着他袖口。与此同时，院里所有雨声猛地一乱，像有几十个人在不同地方同时开口，却又听不清在说什么。</p>\n<p>沈砚再顾不得遮掩，反手掏出那半枚黑片，冲着老妇人眼前一晃。</p>\n<p>那东西一离手，整间堂屋像被什么扯了一下。</p>\n<p>烛火早灭，屋里本该昏暗，可黑片表面却浮出一层极淡的灰光。不是照亮，更像把别的光都吸走了。老妇人喉咙里的咕噜声顿住，眼珠慢慢往上翻，像被人掐住脖子。门外祠堂方向也传来几声闷响，像尸体在泥里翻身。</p>\n<p>沈砚心里一沉，立刻把黑片握回掌中。</p>\n<p>灰光熄了。</p>\n<p>堂屋重归雨声，老妇人的下巴“咔”地垂落，再没一点动静。</p>\n<p>沈砚站在原地，后背一片冷汗。</p>\n<p>他明白两件事。</p>\n<p>第一，这东西确实不该碰。</p>\n<p>第二，它已经碰上他了。</p>\n<p>院外忽然传来瘦猴尖叫：“老邢！老邢！那边尸堆动了！”</p>\n<p>紧接着是铁锹落地的声响，夹着老邢破口大骂：“鬼叫什么！”</p>\n<p>骂声只到一半，突然断了。</p>\n<p>沈砚眼神一变，收起黑片，拖着村正就往外走。现在不能叫人看见他在堂屋里磨蹭，更不能让人知道这异样和他有关。村正的尸体在泥地里磨过去，衣料破开，露出胸前一块青黑。沈砚没细看，只闷头把人往院门拖。</p>\n<p>刚到门口，老邢就冲了进来，脸上没了血色，伞也丢了。</p>\n<p>“快，快把这边弄完。”他声音发紧，“埋了就走。”</p>\n<p>沈砚扫了他一眼：“外头怎么了？”</p>\n<p>“少问。”老邢一把扯过绳子，又立刻撒手，像嫌晦气，“刚才尸堆里有个睁眼了。娘的，死透了还睁眼。”</p>\n<p>瘦猴也跟着冲进来，浑身是泥，嘴唇直哆嗦：“它、它冲我笑。”</p>\n<p>“闭嘴！”</p>\n<p>老邢抬脚要踹，却踹了个空。他自己脚下打滑，扶着门框才站稳。雨夜里，几个人都喘得厉害，谁也不想在这地方多留。</p>\n<p>沈砚低头看向被自己拖到一半的村正。</p>\n<p>村正脸朝下，后脑勺缺了一块，按理说连气都不该剩。他忽然想起方才老妇人盯着的是他的袖口，不是他的脸。</p>\n<p>老邢催道：“愣着做什么，拖啊！”</p>\n<p>沈砚没动，反而蹲下来，把村正翻了个面。</p>\n<p>老邢骂声卡在喉咙里。</p>\n<p>村正的眼睛是闭着的，嘴角却有泥水在往外冒。不是雨打进去的，像是喉咙里有东西在往上顶。</p>\n<p>瘦猴倒吸一口凉气，转身就要跑。</p>\n<p>下一刻，村正的眼皮忽然抖了一下。</p>\n<p>很轻。</p>\n<p>像风掠过死鱼的膜。</p>\n<p>然后，他睁开了眼。</p>\n<p>那双眼被雨泡得发白，没有半点活人光泽，却直直越过老邢和瘦猴，盯住沈砚。泥水顺着他睫毛往下淌，他嘴唇张了两次，牙齿磕出细碎的响。</p>\n<p>老邢“啊”地一声，踉跄后退，撞在门框上。</p>\n<p>瘦猴已经坐到泥里，裤裆湿了一片，不知是雨还是尿。</p>\n<p>沈砚站着没退，手里短刀一点点抬起来。</p>\n<p>他知道，活人装鬼，多半是为了骗人。死人开口，就不是骗那么简单。</p>\n<p>村正盯着他，喉咙里翻出一股带血的气，声音像烂布从井里拽出来。</p>\n<p>“阿……照……”</p>\n<p>短刀停在半空。</p>\n<p>沈砚浑身的血像被这两个字一下冻住。</p>\n<p>这个名字，除了他自己，没人知道。</p>\n<p>连他都快忘了。</p>\n<p>村正嘴角裂开，像想笑，又像整张脸正被什么东西从里面撑开。</p>\n<p>“灯……”</p>\n<p>他才吐出这一个字，沈砚已经一步上前，短刀从他下颌猛地捅进去，直没到柄。</p>\n<p>村正的后脑在泥里抽了一下，眼珠缓缓转向天，嘴还张着，没来得及合上。</p>\n<p>雨劈头盖脸砸下来，把沈砚半边袖口冲得冰凉。</p>\n<p>那半枚黑片贴在腕骨上，像一只重新睁开的眼。</p>\n"}